goasyncio/__init__.py
goasyncio/client.py
goasyncio/server.py
goasyncio/utils.py
goasyncio-1.0.0.dist-info/licenses/LICENSE
goasyncio-1.0.0.dist-info/METADATA
goasyncio-1.0.0.dist-info/WHEEL
goasyncio-1.0.0.dist-info/entry_points.txt
goasyncio-1.0.0.dist-info/top_level.txt
goasyncio-1.0.0.dist-info/RECORD
